setup.py
diandao/__init__.py
diandao/djson.py
diandao/exceptions.py
diandao/filehash.py
diandao/func.py
diandao/rpc.py
diandao.egg-info/PKG-INFO
diandao.egg-info/SOURCES.txt
diandao.egg-info/dependency_links.txt
diandao.egg-info/not-zip-safe
diandao.egg-info/requires.txt
diandao.egg-info/top_level.txt
diandao/flask/__init__.py
diandao/flask/api_clients.py
diandao/flask/application.py
diandao/flask/cacheable.py
diandao/flask/globals.py
diandao/flask/mail.py
diandao/flask/rpc_interface.py
diandao/flask/sqllog.py
diandao/sqlalchemy/__init__.py
diandao/sqlalchemy/types.py